meraki_cli/__init__.py
meraki_cli/__main__.py
meraki_cli/__version__.py
tests/Function.py
tests/ParsedArgs.py
tests/__init__.py
tests/test_args_class.py
tests/test_args_from_file.py
tests/test_build_parser.py
tests/test_check_for_key.py
tests/test_clean_args.py
tests/test_column_filter.py
tests/test_doc_versions.py
tests/test_extra_args_to_kwargs.py
tests/test_helps.py
tests/test_is_json.py
tests/test_log_exception.py
tests/test_logger.py
tests/test_main.py
tests/test_method_params.py
tests/test_nice_table.py
tests/test_normalize_listofdicts.py
tests/test_object_filter.py
tests/test_output.py
tests/test_parser.py
tests/test_print_commands.py
tests/test_reconcile_args.py
tests/test_stdin.py
tests/test_table_ready_dicts.py
tests/test_translations.py
tests/test_upgrade.py
tests/test_user_agent.py
meraki_cli-1.5.1.dist-info/LICENSE
meraki_cli-1.5.1.dist-info/METADATA
meraki_cli-1.5.1.dist-info/WHEEL
meraki_cli-1.5.1.dist-info/entry_points.txt
meraki_cli-1.5.1.dist-info/top_level.txt
meraki_cli-1.5.1.dist-info/RECORD
