Metadata-Version: 2.1
Name: meraki-cli
Version: 1.5.1
Summary: A Simple CLI tool to automate and control your Meraki Dashboard
Home-page: https://github.com/PackeTsar/meraki-cli
Author: John W Kerns
Author-email: jkerns@packetsar.com
License: GNU
Classifier: Development Status :: 5 - Production/Stable
Classifier: Environment :: Console
Classifier: Intended Audience :: Information Technology
Classifier: License :: OSI Approved :: MIT License
Classifier: Natural Language :: English
Classifier: Operating System :: MacOS
Classifier: Operating System :: POSIX
Classifier: Operating System :: Microsoft
Classifier: Operating System :: OS Independent
Classifier: Programming Language :: Python
Classifier: Programming Language :: Python :: 3.10
Classifier: Programming Language :: Python :: 3.11
Classifier: Programming Language :: Python :: 3.12
Classifier: Programming Language :: Python :: 3.13
Classifier: Topic :: Internet
Classifier: Topic :: Utilities
Classifier: Topic :: Software Development :: Libraries :: Python Modules
Classifier: Topic :: System
Classifier: Topic :: System :: Networking
License-File: LICENSE
Requires-Dist: meraki>=1.4.3
Requires-Dist: rich
Requires-Dist: argcomplete
Requires-Dist: jinja2
Provides-Extra: dev
Requires-Dist: jinja2; extra == "dev"
Requires-Dist: pytest; extra == "dev"
Requires-Dist: coverage; extra == "dev"
Requires-Dist: flake8; extra == "dev"
Requires-Dist: requests-mock; extra == "dev"
Requires-Dist: tox; extra == "dev"
Requires-Dist: mkdocs; extra == "dev"
Requires-Dist: mkdocs-material; extra == "dev"
